kafka_healthcheck/__init__.py
kafka_healthcheck/handler.py
kafka_healthcheck/health.py
kafka_healthcheck/main.py
kafka_healthcheck/parser.py
kafka_healthcheck/version.py
kafka_healthcheck-0.0.1.dist-info/LICENSE
kafka_healthcheck-0.0.1.dist-info/METADATA
kafka_healthcheck-0.0.1.dist-info/WHEEL
kafka_healthcheck-0.0.1.dist-info/entry_points.txt
kafka_healthcheck-0.0.1.dist-info/top_level.txt
kafka_healthcheck-0.0.1.dist-info/RECORD
