Metadata-Version: 2.1
Name: kafka-healthcheck
Version: 0.0.1
Summary: A simple healthcheck wrapper to monitor kafka with kafkacat.
Home-page: https://github.com/rodrigongarcia/kafka-healthcheck
Author: Rodrigo Garcia fork of Shawn Seymour
Author-email: rodrigo.garcia@despgar.com, shawn@devshawn.com
License: Apache License 2.0
Keywords: kafka,health,healthcheck,wrapper,monitor
Platform: UNKNOWN
Classifier: Development Status :: 4 - Beta
Classifier: Intended Audience :: Developers
Classifier: Intended Audience :: System Administrators
Classifier: License :: OSI Approved :: Apache Software License
Classifier: Natural Language :: English
Classifier: Operating System :: Unix
Classifier: Programming Language :: Python :: 3.9
Classifier: Topic :: Software Development :: Libraries :: Python Modules
License-File: LICENSE
